pyqsar/__init__.py
pyqsar/classification.py
pyqsar/data_setting.py
pyqsar/data_tools.py
pyqsar/draw_mol.py
pyqsar/minisom.py
pyqsar/model_tools.py
pyqsar3-1.4.3.dist-info/LICENSE.AGPL3
pyqsar3-1.4.3.dist-info/METADATA
pyqsar3-1.4.3.dist-info/WHEEL
pyqsar3-1.4.3.dist-info/top_level.txt
pyqsar3-1.4.3.dist-info/RECORD
