Metadata-Version: 2.1
Name: pyqsar3
Version: 1.4.3
Summary: SSU Lab Package for PYQSAR
Home-page: https://github.com/Chemoinfomatics/pyqsar3
Author: SSU@Chemoinformatic Lab
Author-email: chokh@ssu.ac.kr
License-File: LICENSE.AGPL3
